{ "Countries" : [
{ "key" : "VI" ,
 "name" : "American Virgin Islands" },
{ "key" : "AU" ,
 "name" : "Australia" },
{ "key" : "BH" ,
 "name" : "Bahrain" },
{ "key" : "BE" ,
 "name" : "Belgium" },
{ "key" : "BR" ,
 "name" : "Brazil" },
{ "key" : "CA" ,
 "name" : "Canada" },
{ "key" : "CN" ,
 "name" : "China" },
{ "key" : "CZ" ,
 "name" : "Czech Republic" },
{ "key" : "FI" ,
 "name" : "Finland" },
{ "key" : "FR" ,
 "name" : "France" },
{ "key" : "DE" ,
 "name" : "Germany" },
{ "key" : "GR" ,
 "name" : "Greece" },
{ "key" : "HK" ,
 "name" : "Hong Kong" },
{ "key" : "HU" ,
 "name" : "Hungary" },
{ "key" : "IS" ,
 "name" : "Iceland" },
{ "key" : "IN" ,
 "name" : "India" },
{ "key" : "ID" ,
 "name" : "Indonesia" },
{ "key" : "IR" ,
 "name" : "Iran" },
{ "key" : "IQ" ,
 "name" : "Iraq" },
{ "key" : "IE" ,
 "name" : "Ireland" },
{ "key" : "IL" ,
 "name" : "Israel" },
{ "key" : "IT" ,
 "name" : "Italy" },
{ "key" : "MY" ,
 "name" : "Malaysia" },
{ "key" : "NG" ,
 "name" : "Nigeria" },
{ "key" : "PH" ,
 "name" : "Philippines" },
{ "key" : "ZA" ,
 "name" : "South Africa" },
{ "key" : "KR" ,
 "name" : "South Korea" },
{ "key" : "ES" ,
 "name" : "Spain" },
{ "key" : "LK" ,
 "name" : "Sri Lanka" },
{ "key" : "SE" ,
 "name" : "Sweden" },
{ "key" : "CH" ,
 "name" : "Switzerland" },
{ "key" : "SY" ,
 "name" : "Syria" },
{ "key" : "TW" ,
 "name" : "Taiwan" },
{ "key" : "TH" ,
 "name" : "Thailand" },
{ "key" : "TR" ,
 "name" : "Turkey" },
{ "key" : "US" ,
 "name" : "USA" },
{ "key" : "AE" ,
 "name" : "United Arab Emirates" },
{ "key" : "GB" ,
 "name" : "United Kingdom" },
{ "key" : "VN" ,
 "name" : "Vietnam" },
{ "key" : "ZW" ,
 "name" : "Zimbabwe" }
] }